deep_research_lite/__init__.py
deep_research_lite-0.0.0.dist-info/METADATA
deep_research_lite-0.0.0.dist-info/WHEEL
deep_research_lite-0.0.0.dist-info/RECORD
